terminal_ascii_player-1.0.1.dist-info/licenses/LICENSE
terminal_media_player/__init__.py
terminal_media_player/cli.py
terminal_media_player/player.py
terminal_media_player/utils.py
terminal_ascii_player-1.0.1.dist-info/METADATA
terminal_ascii_player-1.0.1.dist-info/WHEEL
terminal_ascii_player-1.0.1.dist-info/entry_points.txt
terminal_ascii_player-1.0.1.dist-info/top_level.txt
terminal_ascii_player-1.0.1.dist-info/RECORD
